{
    "list": [
        {
            "nodeid": 10901,
            "acquireExp": 0,
            "acquireTotalExpForPersonality": 0,
            "normalClearRewards": [],
            "exClearRewards": [
                {
                    "type": "ITEM",
                    "id": 2,
                    "num": 40
                }
            ]
        },
        {
            "nodeid": 10902,
            "acquireExp": 20,
            "acquireTotalExpForPersonality": 600,
            "normalClearRewards": [],
            "exClearRewards": [
                {
                    "type": "ITEM",
                    "id": 2,
                    "num": 40
                }
            ],
            "exclearConditionTurnCount": 10
        },
        {
            "nodeid": 10903,
            "acquireExp": 20,
            "acquireTotalExpForPersonality": 600,
            "normalClearRewards": [],
            "exClearRewards": [
                {
                    "type": "ITEM",
                    "id": 2,
                    "num": 40
                }
            ],
            "exclearConditionTurnCount": 10
        },{
            "nodeid": 10904,
            "acquireExp": 0,
            "acquireTotalExpForPersonality": 0,
            "normalClearRewards": [],
            "exClearRewards": [
                {
                    "type": "ITEM",
                    "id": 2,
                    "num": 40
                }
            ]
        },
        {
            "nodeid": 10905,
            "acquireExp": 20,
            "acquireTotalExpForPersonality": 600,
            "normalClearRewards": [],
            "exClearRewards": [
                {
                    "type": "ITEM",
                    "id": 2,
                    "num": 40
                }
            ],
            "exclearConditionTurnCount": 10
        },
        {
            "nodeid": 10906,
            "acquireExp": 20,
            "acquireTotalExpForPersonality": 600,
            "normalClearRewards": [],
            "exClearRewards": [
                {
                    "type": "ITEM",
                    "id": 2,
                    "num": 40
                }
            ],
            "exclearConditionTurnCount": 10
        },
        {
            "nodeid": 10907,
            "acquireExp": 0,
            "acquireTotalExpForPersonality": 0,
            "normalClearRewards": [],
            "exClearRewards": [
                {
                    "type": "ITEM",
                    "id": 2,
                    "num": 40
                }
            ]
        },
        {
            "nodeid": 10908,
            "acquireExp": 20,
            "acquireTotalExpForPersonality": 600,
            "normalClearRewards": [],
            "exClearRewards": [
                {
                    "type": "ITEM",
                    "id": 2,
                    "num": 40
                }
            ],
            "exclearConditionTurnCount": 15
        },
        {
            "nodeid": 10909,
            "acquireExp": 20,
            "acquireTotalExpForPersonality": 600,
            "normalClearRewards": [],
            "exClearRewards": [
                {
                    "type": "ITEM",
                    "id": 2,
                    "num": 40
                }
            ],
            "exclearConditionTurnCount": 15
        },
        {
            "nodeid": 10910,
            "acquireExp": 20,
            "acquireTotalExpForPersonality": 600,
            "normalClearRewards": [],
            "exClearRewards": [
                {
                    "type": "ITEM",
                    "id": 2,
                    "num": 40
                }
            ],
            "exclearConditionTurnCount": 15
        },
        {
            "nodeid": 10911,
            "acquireExp": 0,
            "acquireTotalExpForPersonality": 0,
            "normalClearRewards": [],
            "exClearRewards": [
                {
                    "type": "ITEM",
                    "id": 2,
                    "num": 40
                }
            ]
        },
        {
            "nodeid": 10912,
            "acquireExp": 0,
            "acquireTotalExpForPersonality": 0,
            "normalClearRewards": [],
            "exClearRewards": [
                {
                    "type": "ITEM",
                    "id": 2,
                    "num": 40
                }
            ]
        },
        {
            "nodeid": 10913,
            "acquireExp": 0,
            "acquireTotalExpForPersonality": 0,
            "normalClearRewards": [],
            "exClearRewards": [
                {
                    "type": "ITEM",
                    "id": 2,
                    "num": 40
                }
            ]
        },
        {
            "nodeid": 10914,
            "acquireExp": 20,
            "acquireTotalExpForPersonality": 600,
            "normalClearRewards": [],
            "exClearRewards": [
                {
                    "type": "ITEM",
                    "id": 2,
                    "num": 40
                }
            ],
            "exclearConditionTurnCount": 10
        },
        {
            "nodeid": 10915,
            "acquireExp": 20,
            "acquireTotalExpForPersonality": 600,
            "normalClearRewards": [],
            "exClearRewards": [
                {
                    "type": "ITEM",
                    "id": 2,
                    "num": 40
                }
            ],
            "exclearConditionTurnCount": 10
        },
        {
            "nodeid": 10916,
            "acquireExp": 0,
            "acquireTotalExpForPersonality": 0,
            "normalClearRewards": [],
            "exClearRewards": [
                {
                    "type": "ITEM",
                    "id": 2,
                    "num": 40
                }
            ]
        },
        {
            "nodeid": 10917,
            "acquireExp": 20,
            "acquireTotalExpForPersonality": 600,
            "normalClearRewards": [],
            "exClearRewards": [
                {
                    "type": "ITEM",
                    "id": 2,
                    "num": 40
                }
            ],
            "exclearConditionTurnCount": 10
        },
        {
            "nodeid": 10918,
            "acquireExp": 20,
            "acquireTotalExpForPersonality": 600,
            "normalClearRewards": [],
            "exClearRewards": [
                {
                    "type": "ITEM",
                    "id": 2,
                    "num": 40
                }
            ],
            "exclearConditionTurnCount": 99
        }
    ]
}