{
  "list": [
    {
      "personalityID": 10601,
      "battlePassiveList": [
        {
          "level": 1,
          "passiveIDList": [
            1060101
          ]
        }
      ],
      "supporterPassiveList": [
        {
          "level": 3,
          "passiveIDList": [
            1060121
          ]
        }
      ]
    },
    {
      "personalityID": 10602,
      "battlePassiveList": [
        {
          "level": 2,
          "passiveIDList": [
            1060201
          ]
        }
      ],
      "supporterPassiveList": [
        {
          "level": 3,
          "passiveIDList": [
            1060221
          ]
        }
      ]
    },
    {
      "personalityID": 10603,
      "battlePassiveList": [
        {
          "level": 2,
          "passiveIDList": [
            1060301
          ]
        }
      ],
      "supporterPassiveList": [
        {
          "level": 3,
          "passiveIDList": [
            1060321
          ]
        }
      ]
    },
    {
      "personalityID": 10604,
      "battlePassiveList": [
        {
          "level": 2,
          "passiveIDList": [
            1060401
          ]
        }
      ],
      "supporterPassiveList": [
        {
          "level": 3,
          "passiveIDList": [
            1060421
          ]
        }
      ]
    },
    {
      "personalityID": 10605,
      "battlePassiveList": [
        {
          "level": 2,
          "passiveIDList": [
            1060501
          ]
        }
      ],
      "supporterPassiveList": [
        {
          "level": 3,
          "passiveIDList": [
            1060521
          ]
        }
      ]
    },
    {
      "personalityID": 10606,
      "battlePassiveList": [
        {
          "level": 2,
          "passiveIDList": [
            1060601
          ]
        },
        {
          "level": 4,
          "passiveIDList": [
            1060611
          ]
        }
      ],
      "supporterPassiveList": [
        {
          "level": 3,
          "passiveIDList": [
            1060621
          ]
        }
      ]
    },
    {
      "personalityID": 10607,
      "battlePassiveList": [
        {
          "level": 2,
          "passiveIDList": [
            1060701
          ]
        }
      ],
      "supporterPassiveList": [
        {
          "level": 3,
          "passiveIDList": [
            1060721
          ]
        }
      ]
    },
    {
      "personalityID": 10608,
      "battlePassiveList": [
        {
          "level": 2,
          "passiveIDList": [
            1060801
          ]
        },
        {
          "level": 4,
          "passiveIDList": [
            1060811
          ]
        }
      ],
      "supporterPassiveList": [
        {
          "level": 3,
          "passiveIDList": [
            1060821
          ]
        }
      ]
    },
    {
      "personalityID": 10609,
      "battlePassiveList": [
        {
          "level": 2,
          "passiveIDList": [
            1060901
          ]
        }
      ],
      "supporterPassiveList": [
        {
          "level": 3,
          "passiveIDList": [
            1060921
          ]
        }
      ]
    },
    {
      "personalityID": 10610,
      "battlePassiveList": [
        {
          "level": 2,
          "passiveIDList": [
            1061001
          ]
        },
        {
          "level": 4,
          "passiveIDList": [
            1061011
          ]
        }
      ],
      "supporterPassiveList": [
        {
          "level": 3,
          "passiveIDList": [
            1061021
          ]
        }
      ]
    },
    {
      "personalityID": 10611,
      "battlePassiveList": [
        {
          "level": 1,
          "passiveIDList": [
            1061101
          ]
        },
        {
          "level": 2,
          "passiveIDList": [
            1061101,
            1061102
          ]
        },
        {
          "level": 4,
          "passiveIDList": [
            1061101,
            1061111
          ]
        }
      ],
      "supporterPassiveList": [
        {
          "level": 3,
          "passiveIDList": [
            1061121
          ]
        }
      ]
    },
    {
      "personalityID": 10612,
      "battlePassiveList": [
        {
          "level": 2,
          "passiveIDList": [
            1061201
          ]
        },
        {
          "level": 4,
          "passiveIDList": [
            1061211
          ]
        }
      ],
      "supporterPassiveList": [
        {
          "level": 3,
          "passiveIDList": [
            1061221
          ]
        },
        {
          "level": 4,
          "passiveIDList": [
            1061231
          ]
        }
      ]
    },
    {
      "personalityID": 10613,
      "battlePassiveList": [
        {
          "level": 1,
          "passiveIDList": [
            1061302
          ]
        },
        {
          "level": 2,
          "passiveIDList": [
            1061302,
            1061301
          ]
        }
      ],
      "supporterPassiveList": [
        {
          "level": 3,
          "passiveIDList": [
            1061321
          ]
        }
      ]
    },
    {
      "personalityID": 10614,
      "battlePassiveList": [
        {
          "level": 1,
          "passiveIDList": [
            1061404,
            1061405
          ]
        },
        {
          "level": 2,
          "passiveIDList": [
            1061404,
            1061405,
            1061401
          ]
        },
        {
          "level": 3,
          "passiveIDList": [
            1061404,
            1061405,
            1061401
          ]
        },
        {
          "level": 4,
          "passiveIDList": [
            1061404,
            1061405,
            1061411
          ]
        }
      ],
      "supporterPassiveList": [
        {
          "level": 3,
          "passiveIDList": [
            1061421
          ]
        }
      ]
    },
    {
      "personalityID": 10615,
      "battlePassiveList": [
        {
          "level": 1,
          "passiveIDList": [
            1061502
          ]
        },
        {
          "level": 2,
          "passiveIDList": [
            1061502,
            1061501
          ]
        }
      ],
      "supporterPassiveList": [
        {
          "level": 3,
          "passiveIDList": [
            1061521
          ]
        }
      ]
    }
  ]
}