{
  "defaultOpenOrder": 71,
  "maxOpenOrder": 78,
  "startDate": "2025-05-08T21:00:00.000Z",
  "endDate":"2025-05-14T21:00:00.000Z",
  "openConditionChapter": 9116,
  "list": [
        {
      "id": 138,
      "openOrder": 71,
      "openDate": "",
      "titleOrder": 1,
      "days": "984.12.28"
    },
    {
      "id": 139,
      "openOrder": 72,
      "openDate": "",
      "titleOrder": 2,
      "days": "984.12.29"
    },
    {
      "id": 140,
      "openOrder": 73,
      "openDate": "",
      "titleOrder": 2,
      "days": "984.12.30"
    },
    {
      "id": 141,
      "openOrder": 74,
      "openDate": "",
      "titleOrder": 1,
      "days": "984.12.31"
    },
    {
      "id": 142,
      "openOrder": 74,
      "openDate": "",
      "titleOrder": 1,
      "days": "984.12.31"
    },
    {
      "id": 143,
      "openOrder": 75,
      "openDate": "",
      "titleOrder": 1,
      "days": "985.1.01"
    },
    {
      "id": 144,
      "openOrder": 76,
      "openDate": "",
      "titleOrder": 1,
      "days": "985.1.02"
    },
    {
      "id": 145,
      "openOrder": 76,
      "openDate": "",
      "titleOrder": 1,
      "days": "985.1.02"
    },
    {
      "id": 146,
      "openOrder": 77,
      "openDate": "",
      "titleOrder": 1,
      "days": "985.1.03"
    },
    {
      "id": 147,
      "openOrder": 77,
      "openDate": "",
      "titleOrder": 1,
      "days": "985.1.03"
    }
  ]
}