{
  "list": [
    {
      "id": 400005,
      "pivotList": [
        {
          "cutsceneType": "ANOTHER_UNIT_SKILL_0",
          "offsetX": 0,
          "offsetY": 0,
          "closeUp": 1,
          "textureKeyPath": "Assets/Resources_moved/Sprite/Unit/Etc/CG_400005/40000101_1.png"
        },
        {
          "cutsceneType": "ANOTHER_UNIT_SKILL_1",
          "offsetX": 0,
          "offsetY": 0,
          "closeUp": 1,
          "textureKeyPath": "Assets/Resources_moved/Sprite/Unit/Etc/CG_400005/40000101_2.png"
        },
        {
          "cutsceneType": "ANOTHER_UNIT_SKILL_2",
          "offsetX": 0,
          "offsetY": 0,
          "closeUp": 1,
          "textureKeyPath": "Assets/Resources_moved/Sprite/Unit/Etc/CG_400005/40000101_3.png"
        },
        {
          "cutsceneType": "ANOTHER_UNIT_SKILL_3",
          "offsetX": 0,
          "offsetY": 0,
          "closeUp": 1,
          "textureKeyPath": "Assets/Resources_moved/Sprite/Unit/Etc/CG_400005/40000101_4.png"
        },
        {
          "cutsceneType": "ANOTHER_UNIT_SKILL_4",
          "offsetX": 0,
          "offsetY": 0,
          "closeUp": 1,
          "textureKeyPath": "Assets/Resources_moved/Sprite/Unit/Etc/CG_400005/40000102_1.png"
        },
        {
          "cutsceneType": "ANOTHER_UNIT_SKILL_5",
          "offsetX": 0,
          "offsetY": 0,
          "closeUp": 1,
          "textureKeyPath": "Assets/Resources_moved/Sprite/Unit/Etc/CG_400005/40000102_2.png"
        },
        {
          "cutsceneType": "ANOTHER_UNIT_SKILL_6",
          "offsetX": 0,
          "offsetY": 0,
          "closeUp": 1,
          "textureKeyPath": "Assets/Resources_moved/Sprite/Unit/Etc/CG_400005/40000102_3.png"
        },
        {
          "cutsceneType": "ANOTHER_UNIT_SKILL_7",
          "offsetX": 0,
          "offsetY": 0,
          "closeUp": 1,
          "textureKeyPath": "Assets/Resources_moved/Sprite/Unit/Etc/CG_400005/40000102_4.png"
        },
        {
          "cutsceneType": "ANOTHER_UNIT_SKILL_8",
          "offsetX": 0,
          "offsetY": 0,
          "closeUp": 1,
          "textureKeyPath": "Assets/Resources_moved/Sprite/Unit/Etc/CG_400005/40000103_1.png"
        },
        {
          "cutsceneType": "ANOTHER_UNIT_SKILL_9",
          "offsetX": 0,
          "offsetY": 0,
          "closeUp": 1,
          "textureKeyPath": "Assets/Resources_moved/Sprite/Unit/Etc/CG_400005/40000103_2.png"
        },
        {
          "cutsceneType": "ANOTHER_UNIT_SKILL_10",
          "offsetX": 0,
          "offsetY": 0,
          "closeUp": 1,
          "textureKeyPath": "Assets/Resources_moved/Sprite/Unit/Etc/CG_400005/40000103_3.png"
        },
        {
          "cutsceneType": "ANOTHER_UNIT_SKILL_11",
          "offsetX": 0,
          "offsetY": 0,
          "closeUp": 1,
          "textureKeyPath": "Assets/Resources_moved/Sprite/Unit/Etc/CG_400005/40000103_4.png"
        },
        {
          "cutsceneType": "ANOTHER_UNIT_SKILL_12",
          "offsetX": 0,
          "offsetY": 0,
          "closeUp": 1,
          "textureKeyPath": "Assets/Resources_moved/Sprite/Unit/Etc/CG_400005/40000106_1.png"
        }
      ]
    }
  ]

}